h2o_secure_store/__init__.py
h2o_secure_store/exception.py
h2o_secure_store/clients/connection_config.py
h2o_secure_store/clients/login.py
h2o_secure_store/clients/auth/token_api_client.py
h2o_secure_store/clients/base/workspace.py
h2o_secure_store/clients/oauth_client/client.py
h2o_secure_store/clients/oauth_client/oauth_client.py
h2o_secure_store/clients/oauth_client/page.py
h2o_secure_store/clients/secret/client.py
h2o_secure_store/clients/secret/page.py
h2o_secure_store/clients/secret/secret.py
h2o_secure_store/clients/secret/state.py
h2o_secure_store/clients/secret_version/client.py
h2o_secure_store/clients/secret_version/page.py
h2o_secure_store/clients/secret_version/secret_version.py
h2o_secure_store/clients/token_source/client.py
h2o_secure_store/clients/token_source/page.py
h2o_secure_store/clients/token_source/token_source.py
h2o_secure_store/gen/__init__.py
h2o_secure_store/gen/api_client.py
h2o_secure_store/gen/configuration.py
h2o_secure_store/gen/exceptions.py
h2o_secure_store/gen/model_utils.py
h2o_secure_store/gen/rest.py
h2o_secure_store/gen/ai/h2o/securestore/v1/oauth_client_pb2.py
h2o_secure_store/gen/ai/h2o/securestore/v1/oauth_client_pb2.pyi
h2o_secure_store/gen/ai/h2o/securestore/v1/oauth_client_pb2_grpc.py
h2o_secure_store/gen/ai/h2o/securestore/v1/oauth_client_service_pb2.py
h2o_secure_store/gen/ai/h2o/securestore/v1/oauth_client_service_pb2.pyi
h2o_secure_store/gen/ai/h2o/securestore/v1/oauth_client_service_pb2_grpc.py
h2o_secure_store/gen/ai/h2o/securestore/v1/secret_pb2.py
h2o_secure_store/gen/ai/h2o/securestore/v1/secret_pb2.pyi
h2o_secure_store/gen/ai/h2o/securestore/v1/secret_pb2_grpc.py
h2o_secure_store/gen/ai/h2o/securestore/v1/secret_service_pb2.py
h2o_secure_store/gen/ai/h2o/securestore/v1/secret_service_pb2.pyi
h2o_secure_store/gen/ai/h2o/securestore/v1/secret_service_pb2_grpc.py
h2o_secure_store/gen/ai/h2o/securestore/v1/secret_version_pb2.py
h2o_secure_store/gen/ai/h2o/securestore/v1/secret_version_pb2.pyi
h2o_secure_store-1.3.2.dist-info/METADATA
h2o_secure_store-1.3.2.dist-info/WHEEL
h2o_secure_store-1.3.2.dist-info/RECORD
